[
  {
    "id": "qwfqwf",
    "title": "American Idiot",
    "artist": "Dia Verde",
    "imgUrl": "https://upload.wikimedia.org/wikipedia/pt/3/32/AmericanIdiot.jpg"
  },
  {
    "id": "qwfqwf",
    "title": "Witchcraft",
    "artist": "King Gizzard & The Lizzard Wizard",
    "imgUrl": "https://i1.sndcdn.com/artworks-MQHP28Bed5Fn-0-t240x240.jpg"
  },
  {
    "id": "qwfqwf",
    "title": "N達o sei o que",
    "artist": "Usuario",
    "imgUrl": "https://encrypted-tbn0.gstatic.com/images?q=tbn:ANd9GcQMZNQt_VWVdQlBtGcGnjpiwH0KIwMJkzahcA&s"
  },
  {
    "id": "qwfqwf",
    "title": "Psichedelic rock",
    "artist": "Usuario",
    "imgUrl": "https://encrypted-tbn0.gstatic.com/images?q=tbn:ANd9GcQMZNQt_VWVdQlBtGcGnjpiwH0KIwMJkzahcA&s"
  },
  {
    "id": "qwfqwf",
    "title": "American Idiot",
    "artist": "Dia Verde",
    "imgUrl": "https://upload.wikimedia.org/wikipedia/pt/3/32/AmericanIdiot.jpg"
  },
  {
    "id": "qwfqwf",
    "title": "Witchcraft",
    "artist": "King Gizzard & The Lizzard Wizard",
    "imgUrl": "https://i1.sndcdn.com/artworks-MQHP28Bed5Fn-0-t240x240.jpg"
  },
  {
    "id": "qwfqwf",
    "title": "N達o sei o que",
    "artist": "Usuario",
    "imgUrl": "https://encrypted-tbn0.gstatic.com/images?q=tbn:ANd9GcQMZNQt_VWVdQlBtGcGnjpiwH0KIwMJkzahcA&s"
  },
  {
    "id": "qwfqwf",
    "title": "American Idiot",
    "artist": "Dia Verde",
    "imgUrl": "https://upload.wikimedia.org/wikipedia/pt/3/32/AmericanIdiot.jpg"
  },
  {
    "id": "qwfqwf",
    "title": "Witchcraft",
    "artist": "King Gizzard & The Lizzard Wizard",
    "imgUrl": "https://i1.sndcdn.com/artworks-MQHP28Bed5Fn-0-t240x240.jpg"
  },
  {
    "id": "qwfqwf",
    "title": "N達o sei o que",
    "artist": "Usuario",
    "imgUrl": "https://encrypted-tbn0.gstatic.com/images?q=tbn:ANd9GcQMZNQt_VWVdQlBtGcGnjpiwH0KIwMJkzahcA&s"
  },
  {
    "id": "qwfqwf",
    "title": "Psichedelic rock",
    "artist": "Usuario",
    "imgUrl": "https://encrypted-tbn0.gstatic.com/images?q=tbn:ANd9GcQMZNQt_VWVdQlBtGcGnjpiwH0KIwMJkzahcA&s"
  },
  {
    "id": "qwfqwf",
    "title": "American Idiot",
    "artist": "Dia Verde",
    "imgUrl": "https://upload.wikimedia.org/wikipedia/pt/3/32/AmericanIdiot.jpg"
  },
  {
    "id": "qwfqwf",
    "title": "Witchcraft",
    "artist": "King Gizzard & The Lizzard Wizard",
    "imgUrl": "https://i1.sndcdn.com/artworks-MQHP28Bed5Fn-0-t240x240.jpg"
  },
  {
    "id": "qwfqwf",
    "title": "N達o sei o que",
    "artist": "Usuario",
    "imgUrl": "https://encrypted-tbn0.gstatic.com/images?q=tbn:ANd9GcQMZNQt_VWVdQlBtGcGnjpiwH0KIwMJkzahcA&s"
  }
]
